setup.py
Distribution_Final/Binomialdistribution.py
Distribution_Final/Gaussiandistribution.py
Distribution_Final/Generaldistribution.py
Distribution_Final/__init__.py
Distribution_Final.egg-info/PKG-INFO
Distribution_Final.egg-info/SOURCES.txt
Distribution_Final.egg-info/dependency_links.txt
Distribution_Final.egg-info/not-zip-safe
Distribution_Final.egg-info/top_level.txt